dldna/__init__.py
dldna/chapter_02/__init__.py
dldna/chapter_02/information_theory.py
dldna/chapter_02/pca.py
dldna/chapter_02/statistics.py
dldna/chapter_03/__init__.py
dldna/chapter_03/models.py
dldna/chapter_03/train.py
dldna/chapter_03/train_mnist_visualization.py
dldna/chapter_03/visualization/__init__.py
dldna/chapter_03/visualization/tensorboard_utils.py
dldna/chapter_04/__init__.py
dldna/chapter_04/experiments/__init__.py
dldna/chapter_04/experiments/model_training.py
dldna/chapter_04/models/__init__.py
dldna/chapter_04/models/activations.py
dldna/chapter_04/models/base.py
dldna/chapter_04/models/vision.py
dldna/chapter_04/utils/__init__.py
dldna/chapter_04/utils/data.py
dldna/chapter_04/utils/metrics.py
dldna/chapter_04/utils/visualization.py
dldna/chapter_04/visualization/__init__.py
dldna/chapter_04/visualization/activation.py
dldna/chapter_04/visualization/activations.py
dldna/chapter_04/visualization/gradients.py
dldna/chapter_04/visualization/training.py
dldna/chapter_05/__init__.py
dldna/chapter_05/examples/__init__.py
dldna/chapter_05/examples/train_distributed.py
dldna/chapter_05/experiments/__init__.py
dldna/chapter_05/experiments/advanced.py
dldna/chapter_05/experiments/basic.py
dldna/chapter_05/experiments/distributed.py
dldna/chapter_05/initialization/__init__.py
dldna/chapter_05/initialization/analysis.py
dldna/chapter_05/initialization/base.py
dldna/chapter_05/models/__init__.py
dldna/chapter_05/models/transformer.py
dldna/chapter_05/optimizers/__init__.py
dldna/chapter_05/optimizers/advanced.py
dldna/chapter_05/optimizers/base.py
dldna/chapter_05/optimizers/basic.py
dldna/chapter_05/utils/__init__.py
dldna/chapter_05/visualization/__init__.py
dldna/chapter_05/visualization/gaussian_loss_surface.py
dldna/chapter_05/visualization/loss_surface.py
dldna/chapter_05/visualization/optimization.py
dldna/chapter_05/visualization/train_dynamics.py
dldna/chapter_06/__init__.py
dldna/chapter_06/botorch_optimizer.py
dldna/chapter_06/plot_dropout.py
dldna-0.1.6.dist-info/METADATA
dldna-0.1.6.dist-info/WHEEL
dldna-0.1.6.dist-info/top_level.txt
dldna-0.1.6.dist-info/RECORD
