Metadata-Version: 2.2
Name: dldna
Version: 0.1.6
Summary: Deep Learning DNA: Surviving Architectures and Profound Principles
Home-page: https://github.com/Quantum-Intelligence-Frontier/dldna
Author: Seon Yong Park
Author-email: baida21@naver.com
License: CC BY-NC 4.0
Classifier: Programming Language :: Python :: 3
Classifier: Operating System :: OS Independent
Classifier: Topic :: Scientific/Engineering :: Artificial Intelligence
Classifier: Intended Audience :: Developers
Classifier: Intended Audience :: Science/Research
Requires-Python: >=3.7
Requires-Dist: transformers>=4.30
Requires-Dist: datasets>=2.10
Requires-Dist: tqdm>=4.60
Requires-Dist: pillow>=9.0
Requires-Dist: opencv-python>=4.5
Requires-Dist: seaborn_image
Requires-Dist: torchinfo
Requires-Dist: pyhessian
Requires-Dist: bayesian-optimization
Requires-Dist: botorch
Provides-Extra: visualization
Requires-Dist: manim; extra == "visualization"
Provides-Extra: dev
Requires-Dist: torchinfo; extra == "dev"
Requires-Dist: pyhessian; extra == "dev"
Requires-Dist: gudhi; extra == "dev"
Requires-Dist: PyWavelets; extra == "dev"
Requires-Dist: bayesian-optimization; extra == "dev"
Requires-Dist: botorch; extra == "dev"
Requires-Dist: sentencepiece; extra == "dev"
Provides-Extra: colab
Requires-Dist: transformers>=4.30; extra == "colab"
Requires-Dist: datasets>=2.10; extra == "colab"
Requires-Dist: tqdm>=4.60; extra == "colab"
Requires-Dist: pillow>=9.0; extra == "colab"
Requires-Dist: opencv-python>=4.5; extra == "colab"
Requires-Dist: sentencepiece; extra == "colab"
Provides-Extra: all
Requires-Dist: manim; extra == "all"
Requires-Dist: torchinfo; extra == "all"
Requires-Dist: seaborn_image; extra == "all"
Requires-Dist: pyhessian; extra == "all"
Requires-Dist: gudhi; extra == "all"
Requires-Dist: PyWavelets; extra == "all"
Requires-Dist: bayesian-optimization; extra == "all"
Requires-Dist: botorch; extra == "all"
Requires-Dist: sentencepiece; extra == "all"
Requires-Dist: transformers>=4.30; extra == "all"
Requires-Dist: datasets>=2.10; extra == "all"
Requires-Dist: tqdm>=4.60; extra == "all"
Requires-Dist: pillow>=9.0; extra == "all"
Requires-Dist: opencv-python>=4.5; extra == "all"
Requires-Dist: jupyter>=1.0.0; extra == "all"
Requires-Dist: notebook>=6.5.0; extra == "all"
Requires-Dist: ipykernel>=6.29.0; extra == "all"
Requires-Dist: ipywidgets>=8.1.0; extra == "all"
Requires-Dist: seaborn; extra == "all"
Requires-Dist: torch>=1.13; extra == "all"
Requires-Dist: torchvision>=0.14; extra == "all"
Requires-Dist: torchaudio>=0.13; extra == "all"
Requires-Dist: tensorboard>=2.8; extra == "all"
Requires-Dist: numpy>=1.22; extra == "all"
Requires-Dist: pandas>=1.5; extra == "all"
Requires-Dist: matplotlib>=3.5; extra == "all"
Requires-Dist: scikit-learn>=1.0; extra == "all"
Requires-Dist: scipy>=1.8; extra == "all"
Dynamic: author
Dynamic: author-email
Dynamic: classifier
Dynamic: description
Dynamic: description-content-type
Dynamic: home-page
Dynamic: license
Dynamic: provides-extra
Dynamic: requires-dist
Dynamic: requires-python
Dynamic: summary
